Metadata-Version: 2.1
Name: BorisLogFileDB
Version: 0.3
Summary: python packages about logging, database process and folder or file operation.
Home-page: UNKNOWN
Author: boris.zhang
Author-email: bodiz2007@163.com
License: UNKNOWN
Platform: UNKNOWN
Classifier: Programming Language :: Python :: 3
Classifier: License :: OSI Approved :: MIT License
Classifier: Operating System :: OS Independent
Requires-Python: >=3.7
